{"Gorizia": [{"nome": "Gabriele D'Annunzio", "comune": "Gorizia", "sito": "https://www.dannunzio-fabiani.it", "indirizzi": [{"label": "Istituto Tecnico", "key": null}]}, {"nome": "I.S.I.S. S. Pertini Monfalcone", "comune": "Monfalcone", "sito": "https://www.isispertini.edu.it/", "indirizzi": [{"label": "Istituto Professionale", "key": null}, {"label": "Istituto Tecnico", "key": null}, {"label": "Tecnico · Economico (AFM)", "key": "afm"}]}, {"nome": "Is Dante Alighieri", "comune": "Gorizia", "sito": "https://www.pololicealegorizia.edu.it", "indirizzi": [{"label": "Istituto Magistrale", "key": null}, {"label": "Liceo Classico", "key": "classico"}, {"label": "Liceo Scientifico", "key": "scientifico"}]}, {"nome": "Is G. Brignoli - L. Einaudi - G. Marconi", "comune": "Gradisca D'Isonzo", "sito": "https://www.bem.goiss.edu.it", "indirizzi": [{"label": "Istituto Tecnico", "key": null}, {"label": "Tecnico · Economico (AFM)", "key": "afm"}]}, {"nome": "Isis Galilei-Cossar", "comune": "Gorizia", "sito": "https://www.isisgo.it", "indirizzi": [{"label": "Istituto Professionale", "key": null}, {"label": "Istituto Tecnico", "key": null}, {"label": "Tecnico · Costruzioni (CAT)", "key": null}, {"label": "Tecnico · Economico (AFM)", "key": "afm"}]}, {"nome": "Isis I. Cankar (Lingua Slovena)", "comune": "Gorizia", "sito": "https://www.potep.edu.it", "indirizzi": [{"label": "Istituto Professionale", "key": null}, {"label": "Istituto Tecnico", "key": null}, {"label": "Tecnico · Economico (AFM)", "key": "afm"}]}, {"nome": "Michelangelo Buonarroti", "comune": "Monfalcone", "sito": "https://www.liceomonfalcone.it", "indirizzi": [{"label": "Liceo Classico", "key": "classico"}, {"label": "Liceo Scientifico", "key": "scientifico"}]}, {"nome": "Simon Gregorcic (L.Slovena)", "comune": "Gorizia", "sito": "https://www.solskicenter.net", "indirizzi": [{"label": "Istituto Magistrale", "key": null}, {"label": "Liceo Classico", "key": "classico"}]}], "Pordenone": [{"nome": "I.I.S. G. Leopardi-E. Majorana", "comune": "Pordenone", "sito": "https://www.leomajor.edu.it", "indirizzi": [{"label": "Liceo Classico", "key": "classico"}, {"label": "Liceo Scientifico", "key": "scientifico"}]}, {"nome": "I.S.I.S. Il Tagliamento", "comune": "Spilimbergo", "sito": "https://www.isspilimbergo.edu.it", "indirizzi": [{"label": "Istituto Tecnico", "key": null}, {"label": "Tecnico · Economico (AFM)", "key": "afm"}]}, {"nome": "I.S.I.S. L. Zanussi", "comune": "Pordenone", "sito": "https://www.isiszanussi.edu.it", "indirizzi": [{"label": "Istituto Professionale", "key": null}, {"label": "Istituto Tecnico", "key": null}]}, {"nome": "I.S.I.S. Mattiussi - Pertini", "comune": "Pordenone", "sito": "https://isismattiussipertini.edu.it/", "indirizzi": [{"label": "Tecnico · Costruzioni (CAT)", "key": null}, {"label": "Tecnico · Economico (AFM)", "key": "afm"}]}, {"nome": "I.S.I.S. Sacile - Brugnera", "comune": "Sacile", "sito": "https://www.isissacilebrugnera.edu.it/", "indirizzi": [{"label": "Istituto Professionale", "key": null}, {"label": "Istituto Tecnico", "key": null}, {"label": "Tecnico · Economico (AFM)", "key": "afm"}]}, {"nome": "Is E. Torricelli", "comune": "Maniago", "sito": "https://www.torricellimaniago.edu.it", "indirizzi": [{"label": "Istituto Professionale", "key": null}, {"label": "Liceo Scientifico", "key": "scientifico"}]}, {"nome": "Is G.A. Pujati", "comune": "Sacile", "sito": "https://www.liceipujati.edu.it", "indirizzi": [{"label": "Istituto Magistrale", "key": null}]}, {"nome": "Isis P.Sarpi", "comune": "San Vito Al Tagliamento", "sito": "https://www.paolosarpi.edu.it", "indirizzi": [{"label": "Istituto Professionale", "key": null}, {"label": "Istituto Tecnico", "key": null}, {"label": "Tecnico · Economico (AFM)", "key": "afm"}]}, {"nome": "Istituto Istruzione Superiore F. Flora", "comune": "Pordenone", "sito": "https://www.istitutoflora.edu.it", "indirizzi": [{"label": "Istituto Professionale", "key": null}, {"label": "Tecnico · Economico (AFM)", "key": "afm"}]}, {"nome": "Itst Kennedy", "comune": "Pordenone", "sito": "https://www.itstkennedy.edu.it", "indirizzi": [{"label": "Istituto Tecnico", "key": null}]}, {"nome": "Lic.Scientif. Le Filandiere", "comune": "San Vito Al Tagliamento", "sito": "https://www.liceilefilandiere.edu.it/", "indirizzi": [{"label": "Liceo Scientifico", "key": "scientifico"}]}, {"nome": "Liceo Artistico Statale Enrico Galvani", "comune": "Cordenons", "sito": "https://www.liceoartisticogalvani.edu.it", "indirizzi": []}, {"nome": "Ls M. Grigoletti", "comune": "Pordenone", "sito": "https://www.liceogrigoletti.edu.it/", "indirizzi": [{"label": "Liceo Scientifico", "key": "scientifico"}]}], "Trieste": [{"nome": "A.M. Slomsek-L.Ins.Slovena", "comune": "Trieste", "sito": "https://www.slomsek.edu.it", "indirizzi": [{"label": "Istituto Magistrale", "key": null}]}, {"nome": "Alessandro Volta", "comune": "Trieste", "sito": "https://www.voltatrieste.edu.it", "indirizzi": [{"label": "Istituto Tecnico", "key": null}]}, {"nome": "Da Vinci - Carli - De Sandrinelli", "comune": "Trieste", "sito": "https://www.davincicarli.edu.it", "indirizzi": [{"label": "Istituto Professionale", "key": null}, {"label": "Tecnico · Economico (AFM)", "key": "afm"}]}, {"nome": "F.Preseren-L.Ins.Slovena", "comune": "Trieste", "sito": "https://www.preseren.edu.it", "indirizzi": [{"label": "Liceo Scientifico", "key": "scientifico"}]}, {"nome": "Francesco Petrarca", "comune": "Trieste", "sito": "https://www.liceopetrarcats.edu.it", "indirizzi": [{"label": "Liceo Classico", "key": "classico"}]}, {"nome": "Galileo Galilei", "comune": "Trieste", "sito": "https://www.galileitrieste.it", "indirizzi": [{"label": "Liceo Scientifico", "key": "scientifico"}]}, {"nome": "Grazia Deledda - Max Fabiani", "comune": "Trieste", "sito": "https://www.deleddafabiani.edu.it", "indirizzi": [{"label": "Istituto Tecnico", "key": null}]}, {"nome": "Guglielmo Oberdan", "comune": "Trieste", "sito": "https://www.liceo-oberdan.edu.it", "indirizzi": [{"label": "Liceo Scientifico", "key": "scientifico"}]}, {"nome": "Isis Carducci - Dante", "comune": "Trieste", "sito": "https://www.carduccidante.edu.it", "indirizzi": [{"label": "Istituto Magistrale", "key": null}, {"label": "Liceo Classico", "key": "classico"}]}, {"nome": "Isis Nautico T. Di Savoia - L. Galvani", "comune": "Trieste", "sito": "https://www.nauticogalvani.com", "indirizzi": [{"label": "Istituto Professionale", "key": null}, {"label": "Istituto Tecnico", "key": null}]}, {"nome": "J.Stefan-L.Ins.Slovena", "comune": "Trieste", "sito": "https://www.jozefstefan.org", "indirizzi": [{"label": "Istituto Professionale", "key": null}, {"label": "Istituto Tecnico", "key": null}]}, {"nome": "Liceo Artistico Enrico E Umberto Nordio", "comune": "Trieste", "sito": "https://liceonordio.edu.it/", "indirizzi": []}, {"nome": "Ziga Zois-L.Ins.Slovena", "comune": "Trieste", "sito": "https://www.zigazois.edu.it", "indirizzi": [{"label": "Tecnico · Costruzioni (CAT)", "key": null}]}], "Udine": [{"nome": "Conv. Ann. Lic. Sc. Tarvisio", "comune": "Tarvisio", "sito": "https://Non Disponibile", "indirizzi": []}, {"nome": "Convitto Nazionale", "comune": "San Pietro Al Natisone", "sito": "https://www.cnpd.it", "indirizzi": [{"label": "Liceo Classico", "key": "classico"}, {"label": "Liceo Scientifico", "key": "scientifico"}]}, {"nome": "Convitto Nazionale P. Diacono", "comune": "Cividale Del Friuli", "sito": "https://Non Disponibile", "indirizzi": []}, {"nome": "D'Aquileia", "comune": "Cividale Del Friuli", "sito": "https://www.paolinodaquileia.edu.it", "indirizzi": [{"label": "Istituto Professionale", "key": null}, {"label": "Istituto Tecnico", "key": null}, {"label": "Tecnico · Economico (AFM)", "key": "afm"}]}, {"nome": "D'Aronco", "comune": "Gemona Del Friuli", "sito": "https://www.daronco.edu.it", "indirizzi": [{"label": "Istituto Professionale", "key": null}, {"label": "Istituto Tecnico", "key": null}]}, {"nome": "Deganutti", "comune": "Udine", "sito": "https://www.itsdeganutti.edu.it", "indirizzi": [{"label": "Istituto Professionale", "key": null}, {"label": "Tecnico · Economico (AFM)", "key": "afm"}]}, {"nome": "Della Bassa Friulana", "comune": "San Giorgio Di Nogaro", "sito": "https://www.isisbassafriulana.gov.it", "indirizzi": [{"label": "Istituto Professionale", "key": null}, {"label": "Istituto Tecnico", "key": null}, {"label": "Liceo Scientifico", "key": "scientifico"}, {"label": "Tecnico · Economico (AFM)", "key": "afm"}]}, {"nome": "F.Solari", "comune": "Tolmezzo", "sito": "https://www.iissbassafriulana.gov.it/it", "indirizzi": [{"label": "Istituto Professionale", "key": null}, {"label": "Istituto Tecnico", "key": null}, {"label": "Liceo Scientifico", "key": "scientifico"}, {"label": "Tecnico · Economico (AFM)", "key": "afm"}]}, {"nome": "Iis J. Linussio", "comune": "Pozzuolo Del Friuli", "sito": "https://www.linussio.gov.it", "indirizzi": [{"label": "Istituto Professionale", "key": null}, {"label": "Liceo Scientifico", "key": "scientifico"}, {"label": "Professionale · Alberghiero", "key": null}, {"label": "Tecnico · Economico (AFM)", "key": "afm"}]}, {"nome": "Ipsia G. Ceconi Udine", "comune": "Udine", "sito": "https://www.gceconi.eu", "indirizzi": [{"label": "Istituto Professionale", "key": null}]}, {"nome": "Is V. Manzini", "comune": "San Daniele Del Friuli", "sito": "https://www.isismanzini.edu.it", "indirizzi": [{"label": "Liceo Scientifico", "key": "scientifico"}, {"label": "Tecnico · Costruzioni (CAT)", "key": null}]}, {"nome": "Isis A. Malignani Udine", "comune": "Udine", "sito": "https://www.malignani.ud.it/", "indirizzi": [{"label": "Istituto Tecnico", "key": null}, {"label": "Liceo Scientifico", "key": "scientifico"}]}, {"nome": "Isis Bonaldo Stringher", "comune": "Udine", "sito": "https://www.stringher.it", "indirizzi": [{"label": "Istituto Professionale", "key": null}, {"label": "Professionale · Alberghiero", "key": null}, {"label": "Tecnico · Economico (AFM)", "key": "afm"}]}, {"nome": "Istituto Magistrale Uccellis", "comune": "Udine", "sito": "https://www.educandatouccellis.edu.it", "indirizzi": [{"label": "Istituto Magistrale", "key": null}]}, {"nome": "Istituto Omnicomprensivo I. Bachmann", "comune": "Tarvisio", "sito": "https://www.tarvisioscuole.it", "indirizzi": [{"label": "Liceo Scientifico", "key": "scientifico"}, {"label": "Tecnico · Economico (AFM)", "key": "afm"}]}, {"nome": "Istituto Superiore E.Mattei Latisana", "comune": "Latisana", "sito": "https://www.isislatisana.it", "indirizzi": [{"label": "Istituto Professionale", "key": null}, {"label": "Istituto Tecnico", "key": null}, {"label": "Liceo Scientifico", "key": "scientifico"}, {"label": "Tecnico · Economico (AFM)", "key": "afm"}, {"label": "Tecnico · Informatica/Tecnologico", "key": "informatica"}]}, {"nome": "Itc A. Zanon Udine", "comune": "Udine", "sito": "https://www.itzanon.edu.it", "indirizzi": [{"label": "Tecnico · Economico (AFM)", "key": "afm"}]}, {"nome": "Itg G.G. Marinoni Udine", "comune": "Udine", "sito": "https://www.itmarinoni.edu.it/", "indirizzi": [{"label": "Tecnico · Costruzioni (CAT)", "key": null}]}, {"nome": "Liceo Artistico G. Sello Ud", "comune": "Udine", "sito": "https://www.arteudine.edu.it/", "indirizzi": []}, {"nome": "Liceo Caterina Percoto", "comune": "Udine", "sito": "https://www.liceopercoto.edu.it", "indirizzi": [{"label": "Istituto Magistrale", "key": null}]}, {"nome": "Liceo Classico J. Stellini Udine", "comune": "Udine", "sito": "https://www.stelliniudine.edu.it", "indirizzi": [{"label": "Liceo Classico", "key": "classico"}]}, {"nome": "Liceo Scientifico G. Marinelli Udine", "comune": "Udine", "sito": "https://www.liceomarinelli.edu.it", "indirizzi": [{"label": "Liceo Scientifico", "key": "scientifico"}]}, {"nome": "Liceo Scientifico N. Copernico Udine", "comune": "Udine", "sito": "https://www.liceocopernico.edu.it", "indirizzi": [{"label": "Liceo Scientifico", "key": "scientifico"}]}, {"nome": "Magrini Marchetti", "comune": "Gemona Del Friuli", "sito": "https://www.isismagrinimarchetti.it", "indirizzi": [{"label": "Liceo Scientifico", "key": "scientifico"}, {"label": "Tecnico · Costruzioni (CAT)", "key": null}]}, {"nome": "Paschini - Linussio", "comune": "Tolmezzo", "sito": "https://paschinilinussio.edu.it/", "indirizzi": [{"label": "Istituto Magistrale", "key": null}, {"label": "Istituto Professionale", "key": null}, {"label": "Liceo Scientifico", "key": "scientifico"}, {"label": "Tecnico · Economico (AFM)", "key": "afm"}]}, {"nome": "S. Sabbatini", "comune": "Pozzuolo Del Friuli", "sito": "https://Non Disponibile", "indirizzi": []}]}