{"cod": "10795", "cdsCod": "9211R", "nome": "SCIENZE BIOLOGICHE", "area_cod": "AR_FAR", "area": "Scienze chimiche, biologiche, farmaceutiche ed ambientali", "gruppo": "Triennale", "tipo": "Corso di Laurea", "sede": "MESSINA", "lingua": "Italiano", "_v": 3, "aa_label": "2026/2027", "codicione": "0830106201300002", "sede_cod": "1036", "durata": "3 anni", "crediti": "180", "n_insegnamenti": 23, "insegnamenti": [{"adCod": "676", "nome": "BOTANICA GENERALE", "cfu": 7, "ore": 48, "annoCorso": 1, "periodo": "", "tipo": "Obbligatorio", "lingua": "ITALIANO", "docenti": ["GENOVESE GIUSEPPA"], "schemaId": 13969, "corso_aa": "2026", "ordinamento_aa": 2026, "ssd": "BIOS-01/A", "obiettivi": "", "contenuti": "", "prerequisiti": "", "verifica": "", "metodi": "Lezione, Laboratorio", "testi": ""}, {"adCod": "A005666", "nome": "CHIMICA GENERALE ED ELEMENTI DI STECHIOMETRIA", "cfu": 8, "ore": 60, "annoCorso": 1, "periodo": "", "tipo": "Obbligatorio", "lingua": "ITALIANO", "docenti": ["ARENA CARMELA", "DE LUCA GIOVANNA"], "schemaId": 13969, "corso_aa": "2026", "ordinamento_aa": 2026}, {"adCod": "691", "nome": "CITOLOGIA ED ISTOLOGIA", "cfu": 8, "ore": 60, "annoCorso": 1, "periodo": "", "tipo": "Obbligatorio", "lingua": "ITALIANO", "docenti": ["MAISANO MARIA", "CAPPELLO TIZIANA"], "schemaId": 13969, "corso_aa": "2026", "ordinamento_aa": 2026}, {"adCod": "A005667", "nome": "FISICA E ESERCITAZIONI DI FISICA", "cfu": 8, "ore": 60, "annoCorso": 1, "periodo": "", "tipo": "Obbligatorio", "lingua": "ITALIANO", "docenti": ["CACCAMO MARIA TERESA", "MUNAO' GIANMARCO"], "schemaId": 13969, "corso_aa": "2026", "ordinamento_aa": 2026}, {"adCod": "3882", "nome": "LINGUA INGLESE", "cfu": 6, "ore": 0, "annoCorso": 1, "periodo": "", "tipo": "Obbligatorio", "lingua": "INGLESE", "docenti": [], "schemaId": 13969, "corso_aa": "2026", "ordinamento_aa": 2026, "ssd": "ANGL-01/C", "obiettivi": "ll corso mira a portare lo studente al raggiungimento di un livello di competenza linguistica in inglese equivalente al livello B1 del Quadro Comune Europeo di Riferimento, assicurando un uso autonomo delle principali strutture grammaticali e del lessico tecnico di base. Al termine del percorso, lo studente sarà in grado di comprendere, ascoltare e produrre contenuti in inglese scientifico, interagendo con testi e materiali disciplinari senza difficoltà rilevanti. Conoscere le strutture grammaticali fondamentali della lingua inglese e utilizzarle con autonomia in contesti comunicativi, comprendere il lessico tecnico-scientifico di base, con particolare riferimento ai termini più ricorrenti nei testi e nei materiali disciplinari. Al termine dell’insegnamento lo studente sarà in grado di utilizzare in modo autonomo la grammatica e il lessico tecnico per produrre e comprendere messaggi orali e scritti in inglese scientifico, interagire in conversazioni, comprendere e sintetizzare contenuti scientifici presentati in lingua inglese e applicare le competenze linguistiche acquisite per consultare, comprendere e discutere fonti bibliografiche e materiale didattico.", "contenuti": "", "prerequisiti": "", "verifica": "", "metodi": "Esercitazione", "testi": ""}, {"adCod": "A000642", "nome": "MATEMATICA CON ELEMENTI DI STATISTICA", "cfu": 7, "ore": 54, "annoCorso": 1, "periodo": "", "tipo": "Obbligatorio", "lingua": "ITALIANO", "docenti": ["PENGO RICCARDO"], "schemaId": 13969, "corso_aa": "2026", "ordinamento_aa": 2026}, {"adCod": "7179", "nome": "ZOOLOGIA", "cfu": 8, "ore": 60, "annoCorso": 1, "periodo": "", "tipo": "Obbligatorio", "lingua": "ITALIANO", "docenti": ["BAVIERA COSIMO", "CAPILLO GIOELE"], "schemaId": 13969, "corso_aa": "2026", "ordinamento_aa": 2026, "ssd": "BIOS-03/A", "obiettivi": "", "contenuti": "", "prerequisiti": "", "verifica": "", "metodi": "Lezione, Esercitazione, Laboratorio", "testi": ""}, {"adCod": "452", "nome": "BIOCHIMICA", "cfu": 7, "ore": 42, "annoCorso": 2, "periodo": "", "tipo": "Obbligatorio", "lingua": null, "docenti": [], "schemaId": 13969, "corso_aa": "2026", "ordinamento_aa": 2026}, {"adCod": "595", "nome": "BIOLOGIA MOLECOLARE", "cfu": 7, "ore": 48, "annoCorso": 2, "periodo": "", "tipo": "Obbligatorio", "lingua": null, "docenti": [], "schemaId": 13969, "corso_aa": "2026", "ordinamento_aa": 2026}, {"adCod": "991", "nome": "CHIMICA ORGANICA", "cfu": 7, "ore": 54, "annoCorso": 2, "periodo": "", "tipo": "Obbligatorio", "lingua": null, "docenti": [], "schemaId": 13969, "corso_aa": "2026", "ordinamento_aa": 2026}, {"adCod": "1638", "nome": "ECOLOGIA", "cfu": 7, "ore": 42, "annoCorso": 2, "periodo": "", "tipo": "Obbligatorio", "lingua": null, "docenti": [], "schemaId": 13969, "corso_aa": "2026", "ordinamento_aa": 2026}, {"adCod": "2770", "nome": "GENETICA", "cfu": 7, "ore": 48, "annoCorso": 2, "periodo": "", "tipo": "Obbligatorio", "lingua": null, "docenti": [], "schemaId": 13969, "corso_aa": "2026", "ordinamento_aa": 2026}, {"adCod": "4590", "nome": "MICROBIOLOGIA GENERALE", "cfu": 7, "ore": 48, "annoCorso": 2, "periodo": "", "tipo": "Obbligatorio", "lingua": null, "docenti": [], "schemaId": 13969, "corso_aa": "2026", "ordinamento_aa": 2026}, {"adCod": "191", "nome": "ANATOMIA COMPARATA", "cfu": 7, "ore": 48, "annoCorso": 3, "periodo": "", "tipo": "Obbligatorio", "lingua": null, "docenti": [], "schemaId": 13969, "corso_aa": "2026", "ordinamento_aa": 2026}, {"adCod": "562", "nome": "BIOLOGIA DELLO SVILUPPO", "cfu": 7, "ore": 48, "annoCorso": 3, "periodo": "", "tipo": "Obbligatorio", "lingua": null, "docenti": [], "schemaId": 13969, "corso_aa": "2026", "ordinamento_aa": 2026}, {"adCod": "681", "nome": "BOTANICA SISTEMATICA", "cfu": 6, "ore": 42, "annoCorso": 3, "periodo": "", "tipo": "Obbligatorio", "lingua": null, "docenti": [], "schemaId": 13969, "corso_aa": "2026", "ordinamento_aa": 2026}, {"adCod": "7794", "nome": "ELEMENTI DI VIROLOGIA", "cfu": 7, "ore": 54, "annoCorso": 3, "periodo": "", "tipo": "Opzionale", "lingua": null, "docenti": [], "schemaId": 13969, "corso_aa": "2026", "ordinamento_aa": 2026}, {"adCod": "A001678", "nome": "FISIOLOGIA GENERALE E FARMACOLOGIA", "cfu": 12, "ore": 78, "annoCorso": 3, "periodo": "", "tipo": "Obbligatorio", "lingua": null, "docenti": [], "schemaId": 13969, "corso_aa": "2026", "ordinamento_aa": 2026}, {"adCod": "2619", "nome": "FISIOLOGIA VEGETALE", "cfu": 7, "ore": 48, "annoCorso": 3, "periodo": "", "tipo": "Obbligatorio", "lingua": null, "docenti": [], "schemaId": 13969, "corso_aa": "2026", "ordinamento_aa": 2026}, {"adCod": "A000643", "nome": "IGIENE, ANATOMIA UMANA ED IMMUNOLOGIA CON ELEMENTI DI PATOLOGIA GENERALE", "cfu": 16, "ore": 108, "annoCorso": 3, "periodo": "", "tipo": "Obbligatorio", "lingua": null, "docenti": [], "schemaId": 13969, "corso_aa": "2026", "ordinamento_aa": 2026}, {"adCod": "4485", "nome": "METODOLOGIE BIOCHIMICHE", "cfu": 7, "ore": 54, "annoCorso": 3, "periodo": "", "tipo": "Opzionale", "lingua": null, "docenti": [], "schemaId": 13969, "corso_aa": "2026", "ordinamento_aa": 2026}, {"adCod": "A000638", "nome": "METODOLOGIE DI ANALISI STRUMENTALE", "cfu": 7, "ore": 54, "annoCorso": 3, "periodo": "", "tipo": "Opzionale", "lingua": null, "docenti": [], "schemaId": 13969, "corso_aa": "2026", "ordinamento_aa": 2026}, {"adCod": "5238", "nome": "PROVA FINALE", "cfu": 6, "ore": 0, "annoCorso": 3, "periodo": "", "tipo": "Obbligatorio", "lingua": null, "docenti": [], "schemaId": 13969, "corso_aa": "2026", "ordinamento_aa": 2026}]}